setup.py
redisbloomfilter/__init__.py
redisbloomfilter/bloomfilter.py
redisbloomfilter.egg-info/PKG-INFO
redisbloomfilter.egg-info/SOURCES.txt
redisbloomfilter.egg-info/dependency_links.txt
redisbloomfilter.egg-info/requires.txt
redisbloomfilter.egg-info/top_level.txt