Metadata-Version: 1.1
Name: redisbloomfilter
Version: 0.0.1
Summary: 
